facebookadmanager/__init__.py
facebookadmanager/client.py
facebookadmanager/utils.py
FacebookAdManager-0.1b6.dist-info/DESCRIPTION.rst
FacebookAdManager-0.1b6.dist-info/METADATA
FacebookAdManager-0.1b6.dist-info/metadata.json
FacebookAdManager-0.1b6.dist-info/RECORD
FacebookAdManager-0.1b6.dist-info/top_level.txt
FacebookAdManager-0.1b6.dist-info/WHEEL
