Metadata-Version: 2.0
Name: FacebookAdManager
Version: 0.1b6
Summary: Facebook API Client
Home-page: https://github.com/SemanticSugar/facebookadmanager
Author: Grant Toeppen
Author-email: grant@adroll.com
License: MIT
Keywords: facebook ad manager api client development
Platform: UNKNOWN
Requires-Dist: facebookads (>=2.2.4)
